ShishangZuishiyongdeYuehuiJinnang/README.md
ShishangZuishiyongdeYuehuiJinnang/__init__.py
ShishangZuishiyongdeYuehuiJinnang/__main__.py
ShishangZuishiyongdeYuehuiJinnang/file.epub
ShishangZuishiyongdeYuehuiJinnang/index.html
ShishangZuishiyongdeYuehuiJinnang/css/__init__.py
ShishangZuishiyongdeYuehuiJinnang/css/annotations.css
ShishangZuishiyongdeYuehuiJinnang/css/main.css
ShishangZuishiyongdeYuehuiJinnang/css/normalize.css
ShishangZuishiyongdeYuehuiJinnang/css/popup.css
ShishangZuishiyongdeYuehuiJinnang/font/__init__.py
ShishangZuishiyongdeYuehuiJinnang/font/fontello.eot
ShishangZuishiyongdeYuehuiJinnang/font/fontello.svg
ShishangZuishiyongdeYuehuiJinnang/font/fontello.ttf
ShishangZuishiyongdeYuehuiJinnang/font/fontello.woff
ShishangZuishiyongdeYuehuiJinnang/img/__init__.py
ShishangZuishiyongdeYuehuiJinnang/img/annotator-glyph-sprite.png
ShishangZuishiyongdeYuehuiJinnang/img/annotator-icon-sprite.png
ShishangZuishiyongdeYuehuiJinnang/img/apple-touch-icon.png
ShishangZuishiyongdeYuehuiJinnang/img/cancelfullscreen.png
ShishangZuishiyongdeYuehuiJinnang/img/close.png
ShishangZuishiyongdeYuehuiJinnang/img/fullscreen.png
ShishangZuishiyongdeYuehuiJinnang/img/loader.gif
ShishangZuishiyongdeYuehuiJinnang/img/menu-icon.png
ShishangZuishiyongdeYuehuiJinnang/img/save.png
ShishangZuishiyongdeYuehuiJinnang/img/saved.png
ShishangZuishiyongdeYuehuiJinnang/img/settings-s.png
ShishangZuishiyongdeYuehuiJinnang/img/settings.png
ShishangZuishiyongdeYuehuiJinnang/img/star.png
ShishangZuishiyongdeYuehuiJinnang/js/__init__.py
ShishangZuishiyongdeYuehuiJinnang/js/epub.js
ShishangZuishiyongdeYuehuiJinnang/js/epub.min.js
ShishangZuishiyongdeYuehuiJinnang/js/epub.min.map
ShishangZuishiyongdeYuehuiJinnang/js/hooks.min.js
ShishangZuishiyongdeYuehuiJinnang/js/hooks.min.map
ShishangZuishiyongdeYuehuiJinnang/js/reader.js
ShishangZuishiyongdeYuehuiJinnang/js/reader.js.map
ShishangZuishiyongdeYuehuiJinnang/js/reader.min.js
ShishangZuishiyongdeYuehuiJinnang/js/reader.min.map
shishang_zuishiyongde_yuehui_jinnang-2022.10.11.0.dist-info/METADATA
shishang_zuishiyongde_yuehui_jinnang-2022.10.11.0.dist-info/WHEEL
shishang_zuishiyongde_yuehui_jinnang-2022.10.11.0.dist-info/entry_points.txt
shishang_zuishiyongde_yuehui_jinnang-2022.10.11.0.dist-info/top_level.txt
shishang_zuishiyongde_yuehui_jinnang-2022.10.11.0.dist-info/RECORD
